{"remainingRequest":"/Users/pro/new world/node_modules/babel-loader/lib/index.js!/Users/pro/new world/node_modules/eslint-loader/index.js??ref--3-0!/Users/pro/new world/app/component/demo/demo1/index.jsx","dependencies":[{"path":"/Users/pro/new world/app/component/demo/demo1/index.jsx","mtime":1521609811535},{"path":"/Users/pro/new world/.babelrc","mtime":1521535929596},{"path":"/Users/pro/new world/node_modules/cache-loader/dist/cjs.js","mtime":1521535871442},{"path":"/Users/pro/new world/node_modules/babel-loader/lib/index.js","mtime":1520329890000},{"path":"/Users/pro/new world/node_modules/eslint-loader/index.js","mtime":1499322156000}],"contextDependencies":[],"result":["'use strict';\n\nObject.defineProperty(exports, \"__esModule\", {\n    value: true\n});\n\nvar _react = require('react');\n\nvar _react2 = _interopRequireDefault(_react);\n\nfunction _interopRequireDefault(obj) { return obj && obj.__esModule ? obj : { default: obj }; }\n\nvar Demo1 = function Demo1() {\n    return _react2.default.createElement(\n        'h3',\n        null,\n        'hello'\n    );\n};\n\nexports.default = Demo1;",null]}