{"remainingRequest":"/Users/pro/new world/node_modules/babel-loader/lib/index.js!/Users/pro/new world/node_modules/eslint-loader/index.js??ref--4-0!/Users/pro/new world/app/public/js/apiManager.js","dependencies":[{"path":"/Users/pro/new world/app/public/js/apiManager.js","mtime":1521696301183},{"path":"/Users/pro/new world/.babelrc","mtime":1521535929596},{"path":"/Users/pro/new world/node_modules/cache-loader/dist/cjs.js","mtime":1521535871442},{"path":"/Users/pro/new world/node_modules/babel-loader/lib/index.js","mtime":1520329890000},{"path":"/Users/pro/new world/node_modules/eslint-loader/index.js","mtime":1499322156000}],"contextDependencies":[],"result":["'use strict';\n\nObject.defineProperty(exports, \"__esModule\", {\n    value: true\n});\n\nvar _reactCookie = require('react-cookie');\n\nvar _reactCookie2 = _interopRequireDefault(_reactCookie);\n\nfunction _interopRequireDefault(obj) { return obj && obj.__esModule ? obj : { default: obj }; }\n\nif (process.env.NODE_ENV === 'development') {\n    require('../../../mock/todoList');\n    require('../../../mock/weather');\n}\n\nvar token = _reactCookie2.default.load('token');\nvar postApi = function postApi(path, mock) {\n    if (token) {\n        return path + (mock ? '' : '.mock') + '?token=' + token;\n    } else {\n        return path + (mock ? '' : '.mock?');\n    }\n};\n\nexports.default = {\n    \"ipDress\": postApi(\"https://weixin.jirengu.com/weather/ip\", 1),\n    \"todoList\": postApi('/todoList', 0),\n    \"weatherMock\": postApi('/weather', 0),\n    \"cityId\": postApi(\"https://weixin.jirengu.com/weather/cityid\", 1),\n    \"future24\": postApi(\"https://weixin.jirengu.com/weather/future24h\", 1),\n    \"getNow\": postApi(\"https://weixin.jirengu.com/weather/now\", 1)\n};",null]}